hanthon/__init__.py
hanthon/__main__.py
hanthon/main.py
hanthon-0.0.3.dist-info/LICENSE
hanthon-0.0.3.dist-info/METADATA
hanthon-0.0.3.dist-info/WHEEL
hanthon-0.0.3.dist-info/top_level.txt
hanthon-0.0.3.dist-info/RECORD
