Metadata-Version: 2.1
Name: hanthon
Version: 0.0.3
Summary: Write Python in Chinese
Home-page: https://github.com/flizzywine/Hanthon
Author: flizzywine
Author-email: 1041958497@qq.com
License: UNKNOWN
Platform: UNKNOWN
Classifier: Programming Language :: Python :: 3
Classifier: License :: OSI Approved :: MIT License
Classifier: Operating System :: OS Independent
Requires-Python: >=3.6
